fusion/__init__.py
fusion/fusion.py
fusion/response.py
dotcom-0.1.4.dist-info/METADATA
dotcom-0.1.4.dist-info/WHEEL
dotcom-0.1.4.dist-info/top_level.txt
dotcom-0.1.4.dist-info/RECORD
