Metadata-Version: 2.1
Name: dotcom
Version: 0.1.4
Requires-Dist: uvicorn
